attnseeker/__init__.py
attnseeker/cli.py
attnseeker/core.py
attnseeker-0.1.1.dist-info/licenses/LICENSE
attnseeker-0.1.1.dist-info/METADATA
attnseeker-0.1.1.dist-info/WHEEL
attnseeker-0.1.1.dist-info/entry_points.txt
attnseeker-0.1.1.dist-info/top_level.txt
attnseeker-0.1.1.dist-info/RECORD
